epistemictree/__init__.py
epistemictree/__main__.py
epistemictree/cli.py
epistemictree/epmodel.py
epistemictree/eptree.py
epistemictree/my-languages.so
epistemictree/parser.py
epistemictree/rules.py
epistemictree/test_epistemictree.py
epistemictree/tui.py
epistemictree/utils.py
epistemictree-0.3.dist-info/METADATA
epistemictree-0.3.dist-info/WHEEL
epistemictree-0.3.dist-info/top_level.txt
epistemictree-0.3.dist-info/RECORD
