Metadata-Version: 2.1
Name: epistemictree
Version: 0.3
Summary: Tableau
